<annotation>
	<folder>yzm_after_processed</folder>
	<filename>0DI6.png</filename>
	<path>/Users/arkham/Desktop/yzm_after_processed/0DI6.png</path>
	<source>
		<database>Unknown</database>
	</source>
	<size>
		<width>160</width>
		<height>60</height>
		<depth>1</depth>
	</size>
	<segmented>0</segmented>
	<object>
		<name>0</name>
		<pose>Unspecified</pose>
		<truncated>0</truncated>
		<difficult>0</difficult>
		<bndbox>
			<xmin>13</xmin>
			<ymin>3</ymin>
			<xmax>46</xmax>
			<ymax>49</ymax>
		</bndbox>
	</object>
	<object>
		<name>d</name>
		<pose>Unspecified</pose>
		<truncated>0</truncated>
		<difficult>0</difficult>
		<bndbox>
			<xmin>49</xmin>
			<ymin>4</ymin>
			<xmax>80</xmax>
			<ymax>51</ymax>
		</bndbox>
	</object>
	<object>
		<name>i</name>
		<pose>Unspecified</pose>
		<truncated>0</truncated>
		<difficult>0</difficult>
		<bndbox>
			<xmin>83</xmin>
			<ymin>7</ymin>
			<xmax>101</xmax>
			<ymax>48</ymax>
		</bndbox>
	</object>
	<object>
		<name>6</name>
		<pose>Unspecified</pose>
		<truncated>0</truncated>
		<difficult>0</difficult>
		<bndbox>
			<xmin>112</xmin>
			<ymin>5</ymin>
			<xmax>152</xmax>
			<ymax>52</ymax>
		</bndbox>
	</object>
</annotation>
