<annotation>
	<folder>yzm_after_processed</folder>
	<filename>40s8.png</filename>
	<path>/Users/arkham/Desktop/yzm_after_processed/40s8.png</path>
	<source>
		<database>Unknown</database>
	</source>
	<size>
		<width>160</width>
		<height>60</height>
		<depth>1</depth>
	</size>
	<segmented>0</segmented>
	<object>
		<name>4</name>
		<pose>Unspecified</pose>
		<truncated>0</truncated>
		<difficult>0</difficult>
		<bndbox>
			<xmin>5</xmin>
			<ymin>6</ymin>
			<xmax>46</xmax>
			<ymax>51</ymax>
		</bndbox>
	</object>
	<object>
		<name>0</name>
		<pose>Unspecified</pose>
		<truncated>0</truncated>
		<difficult>0</difficult>
		<bndbox>
			<xmin>46</xmin>
			<ymin>6</ymin>
			<xmax>81</xmax>
			<ymax>51</ymax>
		</bndbox>
	</object>
	<object>
		<name>s</name>
		<pose>Unspecified</pose>
		<truncated>0</truncated>
		<difficult>0</difficult>
		<bndbox>
			<xmin>84</xmin>
			<ymin>16</ymin>
			<xmax>111</xmax>
			<ymax>52</ymax>
		</bndbox>
	</object>
	<object>
		<name>8</name>
		<pose>Unspecified</pose>
		<truncated>0</truncated>
		<difficult>0</difficult>
		<bndbox>
			<xmin>119</xmin>
			<ymin>7</ymin>
			<xmax>151</xmax>
			<ymax>50</ymax>
		</bndbox>
	</object>
</annotation>
