<annotation>
	<folder>yzm_after_processed</folder>
	<filename>bayp.png</filename>
	<path>/Users/arkham/Desktop/yzm_after_processed/bayp.png</path>
	<source>
		<database>Unknown</database>
	</source>
	<size>
		<width>160</width>
		<height>60</height>
		<depth>1</depth>
	</size>
	<segmented>0</segmented>
	<object>
		<name>b</name>
		<pose>Unspecified</pose>
		<truncated>0</truncated>
		<difficult>0</difficult>
		<bndbox>
			<xmin>13</xmin>
			<ymin>8</ymin>
			<xmax>44</xmax>
			<ymax>49</ymax>
		</bndbox>
	</object>
	<object>
		<name>a</name>
		<pose>Unspecified</pose>
		<truncated>0</truncated>
		<difficult>0</difficult>
		<bndbox>
			<xmin>47</xmin>
			<ymin>15</ymin>
			<xmax>79</xmax>
			<ymax>50</ymax>
		</bndbox>
	</object>
	<object>
		<name>y</name>
		<pose>Unspecified</pose>
		<truncated>1</truncated>
		<difficult>0</difficult>
		<bndbox>
			<xmin>79</xmin>
			<ymin>14</ymin>
			<xmax>112</xmax>
			<ymax>60</ymax>
		</bndbox>
	</object>
	<object>
		<name>p</name>
		<pose>Unspecified</pose>
		<truncated>1</truncated>
		<difficult>0</difficult>
		<bndbox>
			<xmin>116</xmin>
			<ymin>13</ymin>
			<xmax>148</xmax>
			<ymax>60</ymax>
		</bndbox>
	</object>
</annotation>
