<annotation>
	<folder>yzm_after_processed</folder>
	<filename>t55u.png</filename>
	<path>/Users/arkham/Desktop/yzm_after_processed/t55u.png</path>
	<source>
		<database>Unknown</database>
	</source>
	<size>
		<width>160</width>
		<height>60</height>
		<depth>1</depth>
	</size>
	<segmented>0</segmented>
	<object>
		<name>t</name>
		<pose>Unspecified</pose>
		<truncated>0</truncated>
		<difficult>0</difficult>
		<bndbox>
			<xmin>9</xmin>
			<ymin>9</ymin>
			<xmax>36</xmax>
			<ymax>50</ymax>
		</bndbox>
	</object>
	<object>
		<name>5</name>
		<pose>Unspecified</pose>
		<truncated>0</truncated>
		<difficult>0</difficult>
		<bndbox>
			<xmin>47</xmin>
			<ymin>6</ymin>
			<xmax>77</xmax>
			<ymax>49</ymax>
		</bndbox>
	</object>
	<object>
		<name>5</name>
		<pose>Unspecified</pose>
		<truncated>0</truncated>
		<difficult>0</difficult>
		<bndbox>
			<xmin>86</xmin>
			<ymin>6</ymin>
			<xmax>113</xmax>
			<ymax>48</ymax>
		</bndbox>
	</object>
	<object>
		<name>u</name>
		<pose>Unspecified</pose>
		<truncated>0</truncated>
		<difficult>0</difficult>
		<bndbox>
			<xmin>116</xmin>
			<ymin>15</ymin>
			<xmax>149</xmax>
			<ymax>50</ymax>
		</bndbox>
	</object>
</annotation>
